carbonizer/carbon.py
carbonizer/cli.py
carbonizer/clipboard.py
carbonizer/example.py
carbonizer/options.py
carbonizer/utils.py
carbonizer-0.3.2.dist-info/entry_points.txt
carbonizer-0.3.2.dist-info/WHEEL
carbonizer-0.3.2.dist-info/METADATA
carbonizer-0.3.2.dist-info/RECORD
